dialog_watson_client/Client.py
dialog_watson_client/DialogResponse.py
dialog_watson_client/Profile.py
dialog_watson_client/WatsonDialogDocument_1.0.xsd
dialog_watson_client/__init__.py
dialog_watson_client/__main__.py
dialog_watson_client/exceptions/ExceptionDialogFile.py
dialog_watson_client/exceptions/__init__.py
dialog_watson_client-1.0.2.dist-info/DESCRIPTION.rst
dialog_watson_client-1.0.2.dist-info/METADATA
dialog_watson_client-1.0.2.dist-info/RECORD
dialog_watson_client-1.0.2.dist-info/WHEEL
dialog_watson_client-1.0.2.dist-info/entry_points.txt
dialog_watson_client-1.0.2.dist-info/metadata.json
dialog_watson_client-1.0.2.dist-info/top_level.txt
