Metadata-Version: 2.0
Name: dialog-watson-client
Version: 1.0.2
Summary: Client for dialog watson module
Home-page: https://github.com/HomeHabbit/dialog-watson-client
Author: Arthur Halet
Author-email: arthurh.halet@gmail.com
License: MIT
Keywords: natural langage dialog robot watson IBM
Platform: ALL
Classifier: Topic :: Software Development :: Libraries
Classifier: License :: OSI Approved :: MIT License
Classifier: Topic :: Communications
Requires-Dist: anyconfig
Requires-Dist: bunch
Requires-Dist: lxml (>=3.5.0)
Requires-Dist: watson-developer-cloud (>=0.3.3)
Provides-Extra: XSD
Requires-Dist: lxml (>=3.5.0); extra == 'XSD'
